biomaj/__init__.py
biomaj/bank.py
biomaj/mongo_connector.py
biomaj/notify.py
biomaj/options.py
biomaj/schema_version.py
biomaj/session.py
biomaj/workflow.py
biomaj/process/__init__.py
biomaj/process/metaprocess.py
biomaj/process/processfactory.py
biomaj-3.1.24.data/scripts/biomaj_migrate_database.py
biomaj-3.1.24.dist-info/LICENSE
biomaj-3.1.24.dist-info/METADATA
biomaj-3.1.24.dist-info/WHEEL
biomaj-3.1.24.dist-info/top_level.txt
biomaj-3.1.24.dist-info/RECORD
