Metadata-Version: 2.1
Name: biomaj
Version: 3.1.24
Summary: BioMAJ
Home-page: http://biomaj.genouest.org
Download-URL: http://biomaj.genouest.org
Author: Olivier Sallou
Author-email: olivier.sallou@irisa.fr
Classifier: Development Status :: 5 - Production/Stable
Classifier: Environment :: Console
Classifier: Natural Language :: English
Classifier: Operating System :: POSIX :: Linux
Classifier: Intended Audience :: Science/Research
Classifier: Topic :: Scientific/Engineering :: Bio-Informatics
Classifier: License :: OSI Approved :: GNU Affero General Public License v3 or later (AGPLv3+)
Classifier: Programming Language :: Python :: 3
Classifier: Programming Language :: Python :: 3.6
License-File: LICENSE
Requires-Dist: biomaj-cli
Requires-Dist: biomaj-core
Requires-Dist: biomaj-user
Requires-Dist: biomaj-download
Requires-Dist: biomaj-process
Requires-Dist: pymongo <4,>=3.2
Requires-Dist: pycurl
Requires-Dist: py-bcrypt
Requires-Dist: drmaa
Requires-Dist: tabulate
Requires-Dist: requests
Requires-Dist: redis
Requires-Dist: elasticsearch
Requires-Dist: influxdb
Requires-Dist: Yapsy ==1.12.2
Requires-Dist: packaging
